sagely/__init__.py
sagely/cache.py
sagely/config.py
sagely/context.py
sagely/import_hook.py
sagely/ipython_magics.py
sagely/langgraph_agent.py
sagely/prompts.py
sagely/sage_agent.py
sagely/tracing.py
sagely/usage_info.py
sagely/widgets.py
sagely-0.1.1.dist-info/licenses/LICENSE.md
sagely-0.1.1.dist-info/METADATA
sagely-0.1.1.dist-info/WHEEL
sagely-0.1.1.dist-info/entry_points.txt
sagely-0.1.1.dist-info/top_level.txt
sagely-0.1.1.dist-info/RECORD
